orthanc.py
orthanc_mock-0.1.0.dist-info/METADATA
orthanc_mock-0.1.0.dist-info/WHEEL
orthanc_mock-0.1.0.dist-info/RECORD
