Metadata-Version: 2.1
Name: orthanc-mock
Version: 0.1.0
Summary: Mock for the python orthanc plugin intended for development
Author: Gabriel Couture
Author-email: gacou54@ulaval.ca
Requires-Python: >=3.8,<4.0
Classifier: Programming Language :: Python :: 3
Classifier: Programming Language :: Python :: 3.8
Classifier: Programming Language :: Python :: 3.9
Classifier: Programming Language :: Python :: 3.10
Classifier: Programming Language :: Python :: 3.11
